.mina/elizabeth.toml
avilla/elizabeth/__init__.py
avilla/elizabeth/account.py
avilla/elizabeth/capability.py
avilla/elizabeth/collector/__init__.py
avilla/elizabeth/collector/connection.py
avilla/elizabeth/connection/__init__.py
avilla/elizabeth/connection/base.py
avilla/elizabeth/connection/util.py
avilla/elizabeth/connection/ws_client.py
avilla/elizabeth/const.py
avilla/elizabeth/exception.py
avilla/elizabeth/perform/__init__.py
avilla/elizabeth/perform/action/__init__.py
avilla/elizabeth/perform/action/activity.py
avilla/elizabeth/perform/action/announcement.py
avilla/elizabeth/perform/action/contact.py
avilla/elizabeth/perform/action/file.py
avilla/elizabeth/perform/action/friend.py
avilla/elizabeth/perform/action/group.py
avilla/elizabeth/perform/action/member.py
avilla/elizabeth/perform/action/message.py
avilla/elizabeth/perform/action/request.py
avilla/elizabeth/perform/context.py
avilla/elizabeth/perform/event/__init__.py
avilla/elizabeth/perform/event/activity.py
avilla/elizabeth/perform/event/friend.py
avilla/elizabeth/perform/event/group.py
avilla/elizabeth/perform/event/member.py
avilla/elizabeth/perform/event/message.py
avilla/elizabeth/perform/event/relationship.py
avilla/elizabeth/perform/event/request.py
avilla/elizabeth/perform/message/deserialize.py
avilla/elizabeth/perform/message/serialize.py
avilla/elizabeth/perform/query/__init__.py
avilla/elizabeth/perform/query/announcement.py
avilla/elizabeth/perform/query/bot.py
avilla/elizabeth/perform/query/file.py
avilla/elizabeth/perform/query/friend.py
avilla/elizabeth/perform/query/group.py
avilla/elizabeth/perform/resource_fetch.py
avilla/elizabeth/protocol.py
avilla/elizabeth/resource.py
avilla/elizabeth/service.py
avilla/elizabeth/utils.py
avilla_elizabeth-1.0.0a33.dist-info/METADATA
avilla_elizabeth-1.0.0a33.dist-info/WHEEL
avilla_elizabeth-1.0.0a33.dist-info/licenses/LICENSE
avilla_elizabeth-1.0.0a33.dist-info/RECORD
